tsafe/__init__.py
tsafe-1.3.1.dist-info/LICENSE
tsafe-1.3.1.dist-info/METADATA
tsafe-1.3.1.dist-info/WHEEL
tsafe-1.3.1.dist-info/RECORD
