Metadata-Version: 2.1
Name: tsafe
Version: 1.3.1
Summary: A module that forces functions to be type safe.
License: MIT
Author: Ethan Illingsworth
Author-email: illingsworth.ethan@gmail.com
Requires-Python: >=3.8,<4.0
Classifier: License :: OSI Approved :: MIT License
Classifier: Programming Language :: Python :: 3
Classifier: Programming Language :: Python :: 3.8
Classifier: Programming Language :: Python :: 3.9
Classifier: Programming Language :: Python :: 3.10
Classifier: Programming Language :: Python :: 3.11
Classifier: Programming Language :: Python :: 3.12
Classifier: Programming Language :: Python :: 3.13
